{"coord":{"lon":75.7,"lat":16.8333},"weather":[{"id":501,"main":"Rain","description":"moderate rain","icon":"10d"}],"base":"stations","main":{"temp":33.4,"feels_like":33.56,"temp_min":33.4,"temp_max":33.4,"pressure":1003,"humidity":36,"sea_level":1003,"grnd_level":937},"visibility":10000,"wind":{"speed":6.63,"deg":259,"gust":5.34},"rain":{"1h":1.01},"clouds":{"all":100},"dt":1655469540,"sys":{"country":"IN","sunrise":1655425452,"sunset":1655472716},"timezone":19800,"id":1275701,"name":"Bijapur","cod":200}
