{"coord":{"lon":75.7,"lat":16.8333},"weather":[{"id":804,"main":"Clouds","description":"overcast clouds","icon":"04d"}],"base":"stations","main":{"temp":27.47,"feels_like":29.07,"temp_min":27.47,"temp_max":27.47,"pressure":1009,"humidity":64,"sea_level":1009,"grnd_level":941},"visibility":10000,"wind":{"speed":8.64,"deg":272,"gust":10.19},"clouds":{"all":100},"dt":1691238315,"sys":{"country":"IN","sunrise":1691195893,"sunset":1691242096},"timezone":19800,"id":1275701,"name":"Bijapur","cod":200}
